cloudflarepy/__init__.py
cloudflarepy/client.py
cloudflarepy/error.py
cloudflarepy/http.py
cloudflarepy-0.1.1.dist-info/METADATA
cloudflarepy-0.1.1.dist-info/WHEEL
cloudflarepy-0.1.1.dist-info/top_level.txt
cloudflarepy-0.1.1.dist-info/RECORD
